django_kmatch/__init__.py
django_kmatch/apps.py
django_kmatch/fields.py
django_kmatch/urls.py
django_kmatch/version.py
django_kmatch/tests/__init__.py
django_kmatch/tests/k_field_tests.py
django_kmatch/tests/models.py
django_kmatch/tests/migrations/0001_initial.py
django_kmatch/tests/migrations/__init__.py
django_kmatch-1.2.0.dist-info/METADATA
django_kmatch-1.2.0.dist-info/RECORD
django_kmatch-1.2.0.dist-info/WHEEL
django_kmatch-1.2.0.dist-info/top_level.txt
