Metadata-Version: 2.1
Name: django-kmatch
Version: 1.2.0
Summary: Django utilities for the kmatch library
Home-page: https://github.com/ambitioninc/django-kmatch
Author: Wes Kendall
Author-email: opensource@ambition.com
License: MIT
Keywords: Django,kmatch,match,dictionary
Platform: UNKNOWN
Classifier: Programming Language :: Python
Classifier: Programming Language :: Python :: 3.6
Classifier: Programming Language :: Python :: 3.7
Classifier: Intended Audience :: Developers
Classifier: License :: OSI Approved :: MIT License
Classifier: Operating System :: OS Independent
Classifier: Framework :: Django
Requires-Dist: jsonfield (==0.9.23)
Requires-Dist: Django (>=2.0)
Requires-Dist: kmatch (>=0.3.0)
